spark_instructor/__init__.py
spark_instructor/client/__init__.py
spark_instructor/client/base.py
spark_instructor/completions/__init__.py
spark_instructor/completions/anthropic_completions.py
spark_instructor/completions/base.py
spark_instructor/completions/databricks_completions.py
spark_instructor/completions/ollama_completions.py
spark_instructor/completions/openai_completions.py
spark_instructor/factory/__init__.py
spark_instructor/factory/anthropic_factory.py
spark_instructor/factory/base.py
spark_instructor/factory/databricks_factory.py
spark_instructor/factory/ollama_factory.py
spark_instructor/factory/openai_factory.py
spark_instructor/py.typed
spark_instructor/registry.py
spark_instructor/response_models.py
spark_instructor/types/__init__.py
spark_instructor/types/base.py
spark_instructor/types/openai_types.py
spark_instructor/udf/__init__.py
spark_instructor/udf/instruct.py
spark_instructor/udf/message_router.py
spark_instructor/utils/__init__.py
spark_instructor/utils/env.py
spark_instructor/utils/image.py
spark_instructor/utils/prompt.py
spark_instructor/utils/types.py
spark_instructor-0.2.5.dist-info/LICENSE
spark_instructor-0.2.5.dist-info/METADATA
spark_instructor-0.2.5.dist-info/WHEEL
spark_instructor-0.2.5.dist-info/entry_points.txt
spark_instructor-0.2.5.dist-info/RECORD
