Metadata-Version: 2.1
Name: spark-instructor
Version: 0.2.5
Summary: A library for building structured LLM responses with Spark
Home-page: https://github.com/TJC-LP/spark-instructor
License: MIT
Author: Richie Caputo
Author-email: rcaputo3@tjclp.com
Requires-Python: >=3.10,<4.0
Classifier: License :: OSI Approved :: MIT License
Classifier: Programming Language :: Python :: 3
Classifier: Programming Language :: Python :: 3.10
Classifier: Programming Language :: Python :: 3.11
Classifier: Programming Language :: Python :: 3.12
Classifier: Programming Language :: Python :: 3.13
Provides-Extra: anthropic
Provides-Extra: databricks
Requires-Dist: anthropic (>=0.40.0,<0.41.0) ; extra == "anthropic"
Requires-Dist: async-timeout (>=4.0.3,<5.0.0)
Requires-Dist: databricks-connect (>=15.0.0,<=15.3.2) ; extra == "databricks"
Requires-Dist: databricks-sdk (>=0.38.0,<0.39.0) ; extra == "databricks"
Requires-Dist: instructor (>=1.6.3,<2.0.0)
Requires-Dist: pandas (>=1.5.3)
Requires-Dist: pyarrow (>=8.0.0)
Requires-Dist: python-dotenv (>=1.0.1,<2.0.0)
Requires-Dist: sparkdantic (>=1.1.0,<2.0.0)
Project-URL: Documentation, https://tjc-lp.github.io/spark-instructor/
Project-URL: Repository, https://github.com/TJC-LP/spark-instructor
